tf_supervised_inference/__init__.py
tf_supervised_inference/data.py
tf_supervised_inference/distributions.py
tf_supervised_inference/linear_model.py
tf_supervised_inference-4.1.0.dist-info/METADATA
tf_supervised_inference-4.1.0.dist-info/RECORD
tf_supervised_inference-4.1.0.dist-info/WHEEL
tf_supervised_inference-4.1.0.dist-info/top_level.txt
