Metadata-Version: 2.1
Name: tf-supervised-inference
Version: 4.1.0
Summary: UNKNOWN
Home-page: UNKNOWN
Author: UNKNOWN
Author-email: UNKNOWN
License: UNKNOWN
Platform: UNKNOWN
Requires-Dist: future (>=0.15.2)
Requires-Dist: setuptools (>=20.2.2)
